axoden/__init__.py
axoden/volume_projections.py
axoden/gui/__init__.py
axoden/gui/gui_projections_quantification.py
axoden/gui/streamlit_app/1_📊️_Axoden.py
axoden/gui/streamlit_app/__init__.py
axoden/gui/streamlit_app/__main__.py
axoden/gui/streamlit_app/app_utils.py
axoden/gui/streamlit_app/pdf_utils.py
axoden/gui/streamlit_app/pages/2_❔️_Tutorial_&_How_To.py
axoden/gui/streamlit_app/pages/3_📖️_Cite_Axoden.py
axoden-1.1.0.dist-info/LICENSE
axoden-1.1.0.dist-info/WHEEL
axoden-1.1.0.dist-info/METADATA
axoden-1.1.0.dist-info/RECORD
