Metadata-Version: 2.1
Name: axoden
Version: 1.1.0
Summary: axoden simplifies the quantification of axonal projections in neuroscience.
Author-email: Raquel Adaia Sandoval Ortega <raqueladaia@gmail.com>
Requires-Python: >= 3.8
Classifier: License :: OSI Approved :: GNU General Public License v3 or later (GPLv3+)
Requires-Dist: tqdm >= 4.0.0
Requires-Dist: numpy >= 1.16.0
Requires-Dist: pandas >= 2.0.0
Requires-Dist: seaborn >= 0.10.0
Requires-Dist: matplotlib >= 3.0.0
Requires-Dist: pillow >= 10.0.0
Requires-Dist: scikit-image >= 0.20.0
Requires-Dist: streamlit >= 1.30.0 ; extra == "gui"
Requires-Dist: streamlit-pdf-viewer >= 0.0.10 ; extra == "gui"
Requires-Dist: pypdf >= 4.0.0 ; extra == "gui"
Project-URL: Home, https://github.com/raqueladaia/AxoDen
Provides-Extra: gui
